komminarlabs_cratedb/__init__.py
komminarlabs_cratedb/_inputs.py
komminarlabs_cratedb/_utilities.py
komminarlabs_cratedb/cluster.py
komminarlabs_cratedb/get_cluster.py
komminarlabs_cratedb/get_organization.py
komminarlabs_cratedb/get_organizations.py
komminarlabs_cratedb/get_project.py
komminarlabs_cratedb/organization.py
komminarlabs_cratedb/outputs.py
komminarlabs_cratedb/project.py
komminarlabs_cratedb/provider.py
komminarlabs_cratedb/pulumi-plugin.json
komminarlabs_cratedb/py.typed
komminarlabs_cratedb/config/__init__.py
komminarlabs_cratedb/config/__init__.pyi
komminarlabs_cratedb/config/vars.py
komminarlabs_cratedb-0.3.0.dist-info/METADATA
komminarlabs_cratedb-0.3.0.dist-info/WHEEL
komminarlabs_cratedb-0.3.0.dist-info/top_level.txt
komminarlabs_cratedb-0.3.0.dist-info/RECORD
